redshift_tool/__init__.py
redshift_tool/redshift_tool.py
redshift_tool-0.4.dist-info/LICENSE.txt
redshift_tool-0.4.dist-info/METADATA
redshift_tool-0.4.dist-info/WHEEL
redshift_tool-0.4.dist-info/top_level.txt
redshift_tool-0.4.dist-info/RECORD
