Metadata-Version: 2.1
Name: redshift-tool
Version: 0.4
Summary: Elegant data load from Pandas to Redshift
Home-page: http://github.com/mkgiitr/redshift_tool
Author: Manish Kumar
Author-email: manish.kumar535@gmail.com
License: MIT
Keywords: Pandas,DataFrame,S3,Redshift,Append,Copy,Upsert,Incremetal Load
Platform: UNKNOWN
Classifier: Development Status :: 4 - Beta
Classifier: License :: OSI Approved :: MIT License
Classifier: Programming Language :: Python :: 2.7
Classifier: Programming Language :: Python :: 3.0
Classifier: Programming Language :: Python :: 3.1
Classifier: Programming Language :: Python :: 3.2
Classifier: Programming Language :: Python :: 3.3
Classifier: Programming Language :: Python :: 3.4
Classifier: Programming Language :: Python :: 3.5
Classifier: Programming Language :: Python :: 3.6
Classifier: Programming Language :: Python :: 3.7
Classifier: Topic :: Software Development :: Libraries :: Python Modules
Requires-Dist: psycopg2
Requires-Dist: pandas
Requires-Dist: numpy
Requires-Dist: boto3
